py_spring_dataflow/__init__.py
py_spring_dataflow/args.py
py_spring_dataflow/envs.py
py_spring_dataflow/params.py
py_spring_dataflow/spring/__init__.py
py_spring_dataflow/spring/cloud/__init__.py
py_spring_dataflow/spring/cloud/task/__init__.py
py_spring_dataflow/spring/cloud/task/task_props.py
py_spring_dataflow/spring/datasource_props.py
py_spring_dataflow-0.5.dist-info/LICENSE
py_spring_dataflow-0.5.dist-info/METADATA
py_spring_dataflow-0.5.dist-info/WHEEL
py_spring_dataflow-0.5.dist-info/RECORD
