Metadata-Version: 2.1
Name: py-spring-dataflow
Version: 0.5
Summary: For working with Spring Cloud Data Flow
Home-page: https://github.com/airndlab/py-spring-dataflow
License: MIT
Keywords: spring,spring-cloud,spring-cloud-data-flow,dataflow
Author: Grig Alex
Author-email: alexengrigdev@gmail.com
Maintainer: AI RnD Lab
Maintainer-email: airndlabot@gmail.com
Requires-Python: >=3.11,<4.0
Classifier: License :: OSI Approved :: MIT License
Classifier: Programming Language :: Python :: 3
Classifier: Programming Language :: Python :: 3.11
Project-URL: Repository, https://github.com/airndlab/py-spring-dataflow.git
